pysunspec_to_pvoutput/__init__.py
pysunspec_to_pvoutput/add_status.py
pysunspec_to_pvoutput/config.py
pysunspec_to_pvoutput/init_logging.py
pysunspec_to_pvoutput/read_and_publish.py
pysunspec_to_pvoutput/file_utils/__init__.py
pysunspec_to_pvoutput/file_utils/file_cache.py
pysunspec_to_pvoutput/file_utils/json_utils.py
pysunspec_to_pvoutput-0.20.4.dist-info/METADATA
pysunspec_to_pvoutput-0.20.4.dist-info/WHEEL
pysunspec_to_pvoutput-0.20.4.dist-info/top_level.txt
pysunspec_to_pvoutput-0.20.4.dist-info/RECORD
